[
  {
    "level": 1,
    "problems": [
      {
        "text": "Find the 3rd term of the sequence: 25, 50, 100, ...",
        "given": { "a1": 25, "r": 2, "n": 3 },
        "formula": "an = a1 × r^(n-1)",
        "distractors": ["an = r^n", "an = a1 × r × n"],
        "answer": 100,
        "hint": "This is a geometric sequence. Each term is multiplied by 2 to get the next.",
        "steps": [
          "Identify the first term (a1 = 25)",
          "Find the common ratio (r = 2)",
          "Use the formula: an = a1 × r^(n-1)",
          "Substitute: a3 = 25 × 2^(3-1)",
          "Calculate: 25 × 2^2 = 25 × 4 = ?"
        ]
      },
      {
        "text": "Find the 4th term of the sequence: 3, 9, 27, ...",
        "given": { "a1": 3, "r": 3, "n": 4 },
        "formula": "an = a1 × r^(n-1)",
        "distractors": ["an = a1 + r^n", "an = r^(n-1)"],
        "answer": 81,
        "hint": "Each term is multiplied by 3. Find the fourth term.",
        "steps": [
          "Identify the first term (a1 = 3)",
          "Find the common ratio (r = 3)",
          "Use the formula: an = a1 × r^(n-1)",
          "Substitute: a4 = 3 × 3^(4-1)",
          "Calculate: 3 × 3^3 = 3 × 27 = ?"
        ]
      }
    ]
  },
  {
    "level": 2,
    "problems": [
      {
        "text": "Find the 5th term of the sequence: 4, 8, 16, ...",
        "given": { "a1": 4, "r": 2, "n": 5 },
        "formula": "an = a1 × r^(n-1)",
        "distractors": ["an = a1 + r × n", "an = a1 ÷ r^(n-1)"],
        "answer": 64,
        "hint": "Multiply each term by 2 to get the next. Calculate the 5th term.",
        "steps": [
          "Identify the first term (a1 = 4)",
          "Find the common ratio (r = 2)",
          "Use the formula: an = a1 × r^(n-1)",
          "Substitute: a5 = 4 × 2^(5-1)",
          "Calculate: 4 × 2^4 = 4 × 16 = ?"
        ]
      },
      {
        "text": "Find the 4th term of the sequence: 7, 14, 28, ...",
        "given": { "a1": 7, "r": 2, "n": 4 },
        "formula": "an = a1 × r^(n-1)",
        "distractors": ["an = a1 × r × n", "an = a1 + r^(n-1)"],
        "answer": 56,
        "hint": "Each term is multiplied by 2. Find the fourth term.",
        "steps": [
          "Identify the first term (a1 = 7)",
          "Find the common ratio (r = 2)",
          "Use the formula: an = a1 × r^(n-1)",
          "Substitute: a4 = 7 × 2^(4-1)",
          "Calculate: 7 × 2^3 = 7 × 8 = ?"
        ]
      }
    ]
  }
]